CONTRIBUTORS
LICENSE
MANIFEST.in
README.md
pyproject.toml
requirements-dist.txt
requirements-nn.txt
requirements-test.txt
requirements-tools.txt
requirements.txt
setup.cfg
setup.py
docs/source/conf.py
toad_fix/__init__.py
toad_fix/c_utils.c
toad_fix/cli.py
toad_fix/cli_test.py
toad_fix/detector.py
toad_fix/impute.py
toad_fix/impute_test.py
toad_fix/merge.c
toad_fix/merge_test.py
toad_fix/metrics.py
toad_fix/metrics_test.py
toad_fix/plot.py
toad_fix/plot_test.py
toad_fix/scorecard.py
toad_fix/scorecard_test.py
toad_fix/selection.py
toad_fix/selection_test.py
toad_fix/stats.py
toad_fix/stats_test.py
toad_fix/transform.py
toad_fix/transform_test.py
toad_fix/version.py
toad_fix.egg-info/PKG-INFO
toad_fix.egg-info/SOURCES.txt
toad_fix.egg-info/dependency_links.txt
toad_fix.egg-info/entry_points.txt
toad_fix.egg-info/requires.txt
toad_fix.egg-info/top_level.txt
toad_fix/commands/__init__.py
toad_fix/commands/detect/__init__.py
toad_fix/commands/evaluate/__init__.py
toad_fix/commands/evaluate/evaluate.py
toad_fix/commands/tree/__init__.py
toad_fix/commands/tree/tree.py
toad_fix/nn/__init__.py
toad_fix/nn/functional.py
toad_fix/nn/functional_test.py
toad_fix/nn/loss.py
toad_fix/nn/loss_test.py
toad_fix/nn/module.py
toad_fix/nn/module_test.py
toad_fix/nn/trainer/__init__.py
toad_fix/nn/trainer/callback.py
toad_fix/nn/trainer/callback_test.py
toad_fix/nn/trainer/earlystop.py
toad_fix/nn/trainer/earlystop_test.py
toad_fix/nn/trainer/event.py
toad_fix/nn/trainer/event_test.py
toad_fix/nn/trainer/history.py
toad_fix/nn/trainer/history_test.py
toad_fix/nn/trainer/metrics.py
toad_fix/nn/trainer/trainer.py
toad_fix/nn/trainer/trainer_test.py
toad_fix/nn/zoo/__init__.py
toad_fix/nn/zoo/autoencoder.py
toad_fix/nn/zoo/autoencoder_test.py
toad_fix/preprocessing/__init__.py
toad_fix/preprocessing/partition.py
toad_fix/preprocessing/partition_test.py
toad_fix/preprocessing/process.py
toad_fix/preprocessing/process_test.py
toad_fix/tadpole/__init__.py
toad_fix/tadpole/base.py
toad_fix/tadpole/func.py
toad_fix/tadpole/utils.py
toad_fix/utils/__init__.py
toad_fix/utils/decorator.py
toad_fix/utils/decorator_test.py
toad_fix/utils/func.py
toad_fix/utils/func_test.py
