Metadata-Version: 2.1
Name: toad-fix
Version: 0.1.4
Summary: toad_fix is dedicated to facilitating model development process, especially for a scorecard.
Home-page: https://github.com/amphibian-dev/toad
Author: ESC Team
Author-email: Secbone <secbone@gmail.com>
License: MIT License
Project-URL: Homepage, https://github.com/amphibian-dev/toad_fix
Project-URL: Documentation, https://toad_fix.readthedocs.io/en/stable/
Project-URL: Repository, https://github.com/amphibian-dev/toad_fix.git
Project-URL: Issues, https://github.com/amphibian-dev/toad_fix/issues
Project-URL: Changelog, https://github.com/amphibian-dev/toad_fix/blob/master/CHANGELOG.md
Classifier: Operating System :: POSIX
Classifier: Operating System :: Microsoft :: Windows
Classifier: Operating System :: MacOS :: MacOS X
Classifier: Programming Language :: Python :: 3.8
Classifier: Programming Language :: Python :: 3.9
Classifier: Programming Language :: Python :: 3.10
Classifier: Programming Language :: Python :: 3.11
Classifier: Programming Language :: Python :: 3.12
Requires-Python: >=3.7
Provides-Extra: nn
Provides-Extra: tools
Provides-Extra: all
License-File: LICENSE
